freezable_dict/__init__.py
freezable_dict-0.1.1.dist-info/METADATA
freezable_dict-0.1.1.dist-info/WHEEL
freezable_dict-0.1.1.dist-info/top_level.txt
freezable_dict-0.1.1.dist-info/RECORD
