Metadata-Version: 2.1
Name: freezable-dict
Version: 0.1.1
Summary: A freezable dictionary object.
Home-page: https://github.com/nolanbconaway/freezable_dict
Author: Nolan Conaway
Author-email: nolanbconaway@gmail.com
License: MIT
Keywords: dictionary,mutability,immutable,mapping
Platform: UNKNOWN
Classifier: Programming Language :: Python :: 3.5
Classifier: Programming Language :: Python :: 3.6
Classifier: Programming Language :: Python :: 3.7
Requires-Python: >=3.5
Provides-Extra: test
Requires-Dist: flake8; extra == 'test'
